smfun/__init__.py
smfun/charfun.py
smfun-0.0.4.dist-info/METADATA
smfun-0.0.4.dist-info/WHEEL
smfun-0.0.4.dist-info/top_level.txt
smfun-0.0.4.dist-info/RECORD
