Metadata-Version: 2.4
Name: smfun
Version: 0.0.4
Summary: This is Python Code for Operations on Strings to find Vowels, Consonants, Spaces, Digits and Special Characters
Home-page: https://github.com/sayed2174/smfun
Author: Mohammed Sayed
Author-email: mohammedcm046@gmail.com
Classifier: Programming Language :: Python :: 3.12
Dynamic: author
Dynamic: author-email
Dynamic: classifier
Dynamic: description
Dynamic: description-content-type
Dynamic: home-page
Dynamic: summary
